libumd/__init__.py
libumd/builder.py
libumd/syntax.py
libumd/wrapper.py
libumd-0.2.dist-info/licenses/LICENSE
test/libumd_test.py
libumd-0.2.dist-info/METADATA
libumd-0.2.dist-info/WHEEL
libumd-0.2.dist-info/top_level.txt
libumd-0.2.dist-info/RECORD
