Metadata-Version: 2.4
Name: libumd
Version: 0.2
Summary: A simple on-runtime module loader
Author-email: juanvel400 <juanvel400@proton.me>
License: MIT
Project-URL: Homepage, https://github.com/juanvel4000/libumd
Project-URL: Repository, https://github.com/juanvel4000/libumd
Keywords: module-loader,plugin,runtime,manifest,dynamic-modules
Classifier: Programming Language :: Python :: 3
Classifier: Operating System :: OS Independent
License-File: LICENSE
Dynamic: license-file
